{
	"#comment": "V7-2",
	"version": 1,
	"objects": [ {
			"objclass": "LevelDefinition",
			"objdata": {
				"Name": "V7-2: Wave Gate",
				"IsVasebreaker": true,
				"AddBonusStartingSun": false,
				"LevelPowerupSet": "LevelPowerupsVasebreaker",
				"Description": "",
				"FirstRewardParam": "moneybag",
				"StageModule": "RTID(BeachStage@LevelModules)",
				"StartingSun": 75,
				"Loot": "RTID(DefaultLoot@LevelModules)",
				"Modules": [ "RTID(VaseBreakerArcade@LevelModules)", "RTID(VaseBreakerProps@.)", "RTID(ZombiesDeadWinCon@LevelModules)", "RTID(DefaultZombieWinCondition@LevelModules)", "RTID(Tide@CurrentLevel)", "RTID(SeedBank@CurrentLevel)", "RTID(CoolDown@CurrentLevel)" ]
			}
		}, {
			"objclass": "PlantCooldownModifierProperties",
			"aliases": [ "CoolDown" ],
			"objdata": {
				"CooldownMultiplier": 0.0
			}
		}, {
			"aliases": [ "Tide" ],
			"objclass": "TideProperties",
			"objdata": {
				"StartingWaveLocation": 9
			}
		}, {
			"aliases": [ "SeedBank" ],
			"objclass": "SeedBankProperties",
			"objdata": {
				"PresetPlantList": [ {
						"PlantType": "lilypad",
						"Level": 1
					} ],
				"SelectionMethod": "preset"
			}
		}, {
			"objclass": "VaseBreakerPresetProperties",
			"aliases": [ "VaseBreakerProps" ],
			"objdata": {
				"MinColumnIndex": 0,
				"MaxColumnIndex": 8,
				"GridSquareExcludelist": [ {
						"mX": 2,
						"mY": 0
					}, {
						"mX": 2,
						"mY": 1
					}, {
						"mX": 2,
						"mY": 2
					}, {
						"mX": 2,
						"mY": 3
					}, {
						"mX": 2,
						"mY": 4
					}, {
						"mX": 4,
						"mY": 0
					}, {
						"mX": 4,
						"mY": 1
					}, {
						"mX": 4,
						"mY": 2
					}, {
						"mX": 4,
						"mY": 3
					}, {
						"mX": 4,
						"mY": 4
					}, {
						"mX": 6,
						"mY": 0
					}, {
						"mX": 6,
						"mY": 1
					}, {
						"mX": 6,
						"mY": 2
					}, {
						"mX": 6,
						"mY": 3
					}, {
						"mX": 6,
						"mY": 4
					} ],
				"Vases": [ {
						"ZombieTypeName": "beach",
						"Count": 6
					}, {
						"ZombieTypeName": "beach_armor1",
						"Count": 6
					}, {
						"ZombieTypeName": "beach_snorkel",
						"Count": 5
					}, {
						"PlantTypeName": "xshot",
						"Count": 6
					}, {
						"PlantTypeName": "ghostpepper",
						"Count": 1
					}, {
						"PlantTypeName": "wallnut",
						"Count": 5
					}, {
						"CollectableTypeName": "sun",
						"Count": 1
					} ],
				"NumColoredPlantVases": 12,
				"NumColoredZombieVases": 0
			}
		} ]
}