{
	"#comment": "7-1",
	"objects": [ {
			"objclass": "LevelDefinition",
			"objdata": {
				"Description": "E  C  L  I  S  E",
				"FirstRewardParam": "lilypad",
				"FirstRewardType": "unlock_plant",
				"FirstIntroNarrative": "BEACH1_INTRO",
				"ReplayIntroNarrative": "BEACH1_INTRO",
				"StartingSun": 50,
				"LevelNumber": 1,
				"Loot": "RTID(DefaultLoot@LevelModules)",
				"Modules": [ "RTID(StandardIntro@LevelModules)", "RTID(DefaultSunDropper@LevelModules)", "RTID(ZombiesDeadWinCon@LevelModules)", "RTID(BeachMowers@LevelModules)", "RTID(SeedBank@CurrentLevel)", "RTID(DefaultZombieWinCondition@LevelModules)", "RTID(Escalation@CurrentLevel)", "RTID(NewWaves@CurrentLevel)", "RTID(Tide@CurrentLevel)", "RTID(GI@CurrentLevel)" ],
				"Name": "7-1: Sandy Shores",
				"StageModule": "RTID(BeachStage@LevelModules)"
			}
		}, {
			"aliases": [ "GI" ],
			"objclass": "InitialGridItemProperties",
			"objdata": {
				"InitialGridItemPlacements": [ {
						"GridX": 2,
						"GridY": 0,
						"TypeName": "lilypad"
					}, {
						"GridX": 2,
						"GridY": 1,
						"TypeName": "lilypad"
					}, {
						"GridX": 2,
						"GridY": 2,
						"TypeName": "lilypad"
					}, {
						"GridX": 2,
						"GridY": 3,
						"TypeName": "lilypad"
					}, {
						"GridX": 2,
						"GridY": 4,
						"TypeName": "lilypad"
					}, {
						"GridX": 3,
						"GridY": 0,
						"TypeName": "lilypad"
					}, {
						"GridX": 3,
						"GridY": 1,
						"TypeName": "lilypad"
					}, {
						"GridX": 3,
						"GridY": 2,
						"TypeName": "lilypad"
					}, {
						"GridX": 3,
						"GridY": 3,
						"TypeName": "lilypad"
					}, {
						"GridX": 3,
						"GridY": 4,
						"TypeName": "lilypad"
					}, {
						"GridX": 4,
						"GridY": 0,
						"TypeName": "lilypad"
					}, {
						"GridX": 4,
						"GridY": 1,
						"TypeName": "lilypad"
					}, {
						"GridX": 4,
						"GridY": 2,
						"TypeName": "lilypad"
					}, {
						"GridX": 4,
						"GridY": 3,
						"TypeName": "lilypad"
					}, {
						"GridX": 4,
						"GridY": 4,
						"TypeName": "lilypad"
					} ]
			}
		}, {
			"aliases": [ "Tide" ],
			"objclass": "TideProperties",
			"objdata": {
				"StartingWaveLocation": 7
			}
		}, {
			"aliases": [ "SeedBank" ],
			"objclass": "SeedBankProperties",
			"objdata": {
				"SelectionMethod": "chooser"
			}
		}, {
			"aliases": [ "Escalation" ],
			"objclass": "LevelEscalationModuleProperties",
			"objdata": {
				"FlagCount": 1,
				"PlantfoodToSpawnCount": 0,
				"PointIncrementPerWave": 0,
				"StartingPoints": -1,
				"WaveManagerProps": "RTID(WaveManager@CurrentLevel)",
				"WavesPerFlag": 10,
				"ZombiePool": [ "RTID(beach_imp@ZombieTypes)" ]
			}
		}, {
			"aliases": [ "NewWaves" ],
			"objclass": "WaveManagerModuleProperties",
			"objdata": {}
		}, {
			"aliases": [ "WaveManager" ],
			"objclass": "WaveManagerProperties",
			"objdata": {
				"WaveSpendingPointIncrement": 0,
				"WaveSpendingPoints": 0,
				"Waves": [ [ "RTID(Wave1@CurrentLevel)" ], [ "RTID(Wave2@CurrentLevel)" ], [ "RTID(Wave3@CurrentLevel)" ], [ "RTID(Wave4@CurrentLevel)" ], [ "RTID(Wave5@CurrentLevel)" ], [ "RTID(Wave6@CurrentLevel)" ], [ "RTID(Wave7@CurrentLevel)" ], [ "RTID(Wave8@CurrentLevel)" ], [ "RTID(Wave9@CurrentLevel)" ], [ "RTID(Wave10@CurrentLevel)" ] ]
			}
		}, {
			"aliases": [ "Wave1" ],
			"objclass": "SpawnZombiesJitteredWaveActionProps",
			"objdata": {
				"Zombies": [ {
						"Row": "4",
						"Type": "RTID(beach@ZombieTypes)"
					} ]
			}
		}, {
			"aliases": [ "Wave2" ],
			"objclass": "SpawnZombiesJitteredWaveActionProps",
			"objdata": {
				"Zombies": [ {
						"Row": "2",
						"Type": "RTID(beach_fem@ZombieTypes)"
					}, {
						"Row": "5",
						"Type": "RTID(beach@ZombieTypes)"
					} ]
			}
		}, {
			"aliases": [ "Wave3" ],
			"objclass": "SpawnZombiesJitteredWaveActionProps",
			"objdata": {
				"Zombies": [ {
						"Row": "3",
						"Type": "RTID(beach_fem_armor1@ZombieTypes)"
					}, {
						"Row": "4",
						"Type": "RTID(beach@ZombieTypes)"
					} ]
			}
		}, {
			"aliases": [ "Wave4" ],
			"objclass": "SpawnZombiesJitteredWaveActionProps",
			"objdata": {
				"Zombies": [ {
						"Row": "1",
						"Type": "RTID(beach@ZombieTypes)"
					}, {
						"Row": "2",
						"Type": "RTID(beach_fem@ZombieTypes)"
					}, {
						"Row": "5",
						"Type": "RTID(beach_fem@ZombieTypes)"
					}, {
						"Row": "5",
						"Type": "RTID(beach@ZombieTypes)"
					} ]
			}
		}, {
			"aliases": [ "Wave5" ],
			"objclass": "SpawnZombiesJitteredWaveActionProps",
			"objdata": {
				"Zombies": [ {
						"Row": "2",
						"Type": "RTID(beach_armor1@ZombieTypes)"
					}, {
						"Row": "4",
						"Type": "RTID(beach_fem_armor1@ZombieTypes)"
					}, {
						"Row": "5",
						"Type": "RTID(beach_armor1@ZombieTypes)"
					} ]
			}
		}, {
			"aliases": [ "Wave6" ],
			"objclass": "SpawnZombiesJitteredWaveActionProps",
			"objdata": {
				"Zombies": [ {
						"Row": "1",
						"Type": "RTID(beach@ZombieTypes)"
					}, {
						"Row": "2",
						"Type": "RTID(beach_fem@ZombieTypes)"
					}, {
						"Row": "3",
						"Type": "RTID(beach_armor1@ZombieTypes)"
					}, {
						"Row": "4",
						"Type": "RTID(beach@ZombieTypes)"
					}, {
						"Row": "2",
						"Type": "RTID(beach_fem_armor1@ZombieTypes)"
					} ]
			}
		}, {
			"aliases": [ "Wave7" ],
			"objclass": "SpawnZombiesJitteredWaveActionProps",
			"objdata": {
				"Zombies": [ {
						"Row": "1",
						"Type": "RTID(beach_fem_armor1@ZombieTypes)"
					}, {
						"Row": "5",
						"Type": "RTID(beach_fem_armor1@ZombieTypes)"
					}, {
						"Row": "1",
						"Type": "RTID(beach_armor1@ZombieTypes)"
					}, {
						"Row": "5",
						"Type": "RTID(beach_armor1@ZombieTypes)"
					} ]
			}
		}, {
			"aliases": [ "Wave8" ],
			"objclass": "SpawnZombiesJitteredWaveActionProps",
			"objdata": {
				"Zombies": [ {
						"Row": "1",
						"Type": "RTID(beach@ZombieTypes)"
					}, {
						"Row": "2",
						"Type": "RTID(beach_fem@ZombieTypes)"
					}, {
						"Row": "3",
						"Type": "RTID(beach_fem@ZombieTypes)"
					}, {
						"Row": "4",
						"Type": "RTID(beach_armor1@ZombieTypes)"
					}, {
						"Row": "5",
						"Type": "RTID(beach_fem@ZombieTypes)"
					}, {
						"Row": "2",
						"Type": "RTID(beach@ZombieTypes)"
					}, {
						"Row": "3",
						"Type": "RTID(beach_armor1@ZombieTypes)"
					} ]
			}
		}, {
			"aliases": [ "Wave9" ],
			"objclass": "SpawnZombiesJitteredWaveActionProps",
			"objdata": {
				"Zombies": [ {
						"Row": "1",
						"Type": "RTID(beach_armor1@ZombieTypes)"
					}, {
						"Row": "2",
						"Type": "RTID(beach@ZombieTypes)"
					}, {
						"Row": "3",
						"Type": "RTID(beach_fem_armor1@ZombieTypes)"
					}, {
						"Row": "4",
						"Type": "RTID(beach_fem_armor1@ZombieTypes)"
					}, {
						"Row": "1",
						"Type": "RTID(beach@ZombieTypes)"
					}, {
						"Row": "3",
						"Type": "RTID(beach_fem@ZombieTypes)"
					}, {
						"Row": "4",
						"Type": "RTID(beach_fem_armor1@ZombieTypes)"
					} ]
			}
		}, {
			"aliases": [ "Wave10" ],
			"objclass": "SpawnZombiesJitteredWaveActionProps",
			"objdata": {
				"Zombies": [ {
						"Row": "1",
						"Type": "RTID(beach_fem_armor1@ZombieTypes)"
					}, {
						"Row": "2",
						"Type": "RTID(beach_fem_armor1@ZombieTypes)"
					}, {
						"Row": "3",
						"Type": "RTID(beach_fem_armor1@ZombieTypes)"
					}, {
						"Row": "4",
						"Type": "RTID(beach_fem_armor1@ZombieTypes)"
					}, {
						"Row": "5",
						"Type": "RTID(beach_armor1@ZombieTypes)"
					}, {
						"Row": "1",
						"Type": "RTID(beach_armor1@ZombieTypes)"
					}, {
						"Row": "2",
						"Type": "RTID(beach_armor1@ZombieTypes)"
					}, {
						"Row": "3",
						"Type": "RTID(beach_armor1@ZombieTypes)"
					}, {
						"Row": "4",
						"Type": "RTID(beach_armor1@ZombieTypes)"
					}, {
						"Row": "5",
						"Type": "RTID(beach_fem_armor1@ZombieTypes)"
					}, {
						"Row": "1",
						"Type": "RTID(beach_fem@ZombieTypes)"
					}, {
						"Row": "2",
						"Type": "RTID(beach@ZombieTypes)"
					}, {
						"Row": "3",
						"Type": "RTID(beach_fem@ZombieTypes)"
					}, {
						"Row": "4",
						"Type": "RTID(beach_fem@ZombieTypes)"
					}, {
						"Row": "5",
						"Type": "RTID(beach_armor1@ZombieTypes)"
					}, {
						"Row": "1",
						"Type": "RTID(beach@ZombieTypes)"
					}, {
						"Row": "2",
						"Type": "RTID(beach_fem@ZombieTypes)"
					}, {
						"Row": "3",
						"Type": "RTID(beach_fem@ZombieTypes)"
					} ]
			}
		}, {
			"aliases": [ "Tide0" ],
			"objclass": "TidalChangeWaveActionProps",
			"objdata": {
				"TidalChange": {
					"ChangeAmount": 0,
					"ChangeType": "absolute"
				}
			}
		}, {
			"aliases": [ "Tide1" ],
			"objclass": "TidalChangeWaveActionProps",
			"objdata": {
				"TidalChange": {
					"ChangeAmount": 1,
					"ChangeType": "absolute"
				}
			}
		}, {
			"aliases": [ "Tide2" ],
			"objclass": "TidalChangeWaveActionProps",
			"objdata": {
				"TidalChange": {
					"ChangeAmount": 2,
					"ChangeType": "absolute"
				}
			}
		}, {
			"aliases": [ "Tide3" ],
			"objclass": "TidalChangeWaveActionProps",
			"objdata": {
				"TidalChange": {
					"ChangeAmount": 3,
					"ChangeType": "absolute"
				}
			}
		}, {
			"aliases": [ "Tide4" ],
			"objclass": "TidalChangeWaveActionProps",
			"objdata": {
				"TidalChange": {
					"ChangeAmount": 4,
					"ChangeType": "absolute"
				}
			}
		}, {
			"aliases": [ "Tide5" ],
			"objclass": "TidalChangeWaveActionProps",
			"objdata": {
				"TidalChange": {
					"ChangeAmount": 5,
					"ChangeType": "absolute"
				}
			}
		}, {
			"aliases": [ "Tide6" ],
			"objclass": "TidalChangeWaveActionProps",
			"objdata": {
				"TidalChange": {
					"ChangeAmount": 6,
					"ChangeType": "absolute"
				}
			}
		}, {
			"aliases": [ "Tide7" ],
			"objclass": "TidalChangeWaveActionProps",
			"objdata": {
				"TidalChange": {
					"ChangeAmount": 7,
					"ChangeType": "absolute"
				}
			}
		}, {
			"aliases": [ "Tide8" ],
			"objclass": "TidalChangeWaveActionProps",
			"objdata": {
				"TidalChange": {
					"ChangeAmount": 8,
					"ChangeType": "absolute"
				}
			}
		}, {
			"aliases": [ "Tide9" ],
			"objclass": "TidalChangeWaveActionProps",
			"objdata": {
				"TidalChange": {
					"ChangeAmount": 9,
					"ChangeType": "absolute"
				}
			}
		}, {
			"aliases": [ "LT1" ],
			"objclass": "BeachStageEventZombieSpawnerProps",
			"objdata": {
				"ColumnEnd": 6,
				"ColumnStart": 3,
				"GroupSize": 6,
				"TimeBeforeFullSpawn": "0.5",
				"TimeBetweenGroups": "0.25",
				"WaveStartMessage": "[WARNING_LOW_TIDE]",
				"ZombieCount": 2,
				"ZombieName": "beach_gargantuar"
			}
		} ],
	"version": 1
}