{
	"#comment": "BB4",
	"objects": [ {
			"objclass": "LevelDefinition",
			"objdata": {
				"Description": "E  C  L  I  S  E",
				"Loot": "RTID(DefaultLoot@LevelModules)",
				"Modules": [ "RTID(StandardIntro@LevelModules)", "RTID(BeachMowers@LevelModules)", "RTID(DefaultSunDropper@LevelModules)", "RTID(ZombiesDeadWinCon@LevelModules)", "RTID(DefaultZombieWinCondition@LevelModules)", "RTID(GridItems@CurrentLevel)", "RTID(ChallengeModule@CurrentLevel)", "RTID(SeedBank@CurrentLevel)", "RTID(Escalation@CurrentLevel)", "RTID(NewWaves@CurrentLevel)" ],
				"Name": "Botanical Battle IV: Bowl Game - DT",
				"StageModule": "RTID(BeachStage@CurrentLevel)"
			}
		}, {
			"objclass": "EightiesStageProperties",
			"aliases": [ "BeachStage" ],
			"objdata": {
				"ResourceGroupNames": [ "DelayLoad_Background_Beach", "DelayLoad_Background_Beach_Compressed", "Dirt_Spawn_Dirt", "AudioBeach", "BeachGroansAudio" ],
				"GroupsToUnloadForAds": [ "DelayLoad_Background_Beach_Compressed" ],
				"StagePrefix": "beach",
				"BackgroundResourceGroup": "DelayLoad_Background_Beach_Compressed",
				"BackgroundImagePrefix": "IMAGE_BACKGROUNDS_BEACH",
				"LevelPowerupSet": "LevelPowerupsDefault",
				"BasicZombieTypeName": "beach",
				"FlagZombieTypeName": "beach_flag",
				"Armor1ZombieTypeName": "beach_armor1",
				"Armor2ZombieTypeName": "beach_armor2",
				"RailcartDefaultTypeName": "railcart_egypt",
				"GravestoneDefaultTypeName": "gravestone_egypt",
				"DirtSpawnEffectName": "POPANIM_EFFECTS_DIRT_SPAWN_DIRT",
				"MusicSuffix": "Beach"
			}
		}, {
			"aliases": [ "GridItems" ],
			"objclass": "InitialGridItemProperties",
			"objdata": {
				"InitialGridItemPlacements": [ {
						"GridX": 30,
						"GridY": 2,
						"TypeName": "traptile_1"
					}, {
						"GridX": -10,
						"GridY": 0,
						"TypeName": "arcadecabinet_lanechange"
					}, {
						"GridX": -10,
						"GridY": 1,
						"TypeName": "arcadecabinet_lanechange"
					}, {
						"GridX": -10,
						"GridY": 2,
						"TypeName": "arcadecabinet_lanechange"
					}, {
						"GridX": -10,
						"GridY": 3,
						"TypeName": "arcadecabinet_lanechange"
					}, {
						"GridX": -10,
						"GridY": 4,
						"TypeName": "arcadecabinet_lanechange"
					} ]
			}
		}, {
			"aliases": [ "ChallengeModule" ],
			"objclass": "StarChallengeModuleProperties",
			"objdata": {
				"Challenges": [ [ "RTID(ChallengeText@CurrentLevel)" ] ],
				"ChallengesAlwaysAvailable": true
			}
		}, {
			"aliases": [ "ChallengeText" ],
			"objclass": "StarChallengeBeatTheLevelProps",
			"objdata": {
				"Description": "Survive while the Bowling Hunters attack!\nThey cannot be stunned!",
				"DescriptiveName": ""
			}
		}, {
			"aliases": [ "SeedBank" ],
			"objclass": "SeedBankProperties",
			"objdata": {
				"PlantExcludeList": [ "caulipower", "chomper", "electricblueberry", "grimrose", "toadstool", "hurrikale", "witchhazel" ],
				"SelectionMethod": "chooser"
			}
		}, {
			"aliases": [ "NewWaves" ],
			"objclass": "WaveManagerModuleProperties",
			"objdata": {}
		}, {
			"aliases": [ "Escalation" ],
			"objclass": "LevelEscalationModuleProperties",
			"objdata": {
				"FlagCount": 3,
				"PlantfoodToSpawnCount": 0,
				"PointIncrementPerWave": 0.0,
				"StartingPoints": 0.0,
				"WaveManagerProps": "RTID(WaveManager@CurrentLevel)",
				"WavesPerFlag": 8,
				"ZombiePool": [ "RTID(dummy@ZombieTypes)" ]
			}
		}, {
			"aliases": [ "WaveManager" ],
			"objclass": "WaveManagerProperties",
			"objdata": {
				"Waves": [ [ "RTID(Wave1@CurrentLevel)", "RTID(Jam8bit@CurrentLevel)", "RTID(BossSpawn@CurrentLevel)" ], [ "RTID(Wave2@CurrentLevel)" ], [ "RTID(Wave3@CurrentLevel)" ], [ "RTID(Wave4@CurrentLevel)" ], [ "RTID(Wave5@CurrentLevel)" ], [ "RTID(Wave6@CurrentLevel)", "RTID(CHMessage@CurrentLevel)", "RTID(CH@CurrentLevel)" ], [ "RTID(Wave7@CurrentLevel)" ], [ "RTID(Wave8@CurrentLevel)", "RTID(BossSpawn@CurrentLevel)" ], [ "RTID(Wave9@CurrentLevel)", "RTID(CHMessage@CurrentLevel)", "RTID(CH@CurrentLevel)" ], [ "RTID(Wave10@CurrentLevel)" ], [ "RTID(Wave11@CurrentLevel)", "RTID(CHMessage@CurrentLevel)", "RTID(CH@CurrentLevel)" ], [ "RTID(Wave12@CurrentLevel)" ], [ "RTID(Wave13@CurrentLevel)" ], [ "RTID(Wave14@CurrentLevel)" ], [ "RTID(Wave15@CurrentLevel)", "RTID(CHMessage@CurrentLevel)", "RTID(CH@CurrentLevel)" ], [ "RTID(Wave16@CurrentLevel)", "RTID(BossSpawn@CurrentLevel)", "RTID(BossSpawn@CurrentLevel)" ], [ "RTID(Wave17@CurrentLevel)", "RTID(CHMessage@CurrentLevel)", "RTID(CH@CurrentLevel)" ], [ "RTID(Wave18@CurrentLevel)" ], [ "RTID(Wave19@CurrentLevel)" ], [ "RTID(Wave20@CurrentLevel)", "RTID(CHMessage@CurrentLevel)", "RTID(CH@CurrentLevel)" ], [ "RTID(Wave21@CurrentLevel)" ], [ "RTID(Wave22@CurrentLevel)" ], [ "RTID(Wave23@CurrentLevel)" ], [ "RTID(Wave24@CurrentLevel)", "RTID(BossSpawn@CurrentLevel)", "RTID(BossSpawn@CurrentLevel)", "RTID(CHMessage@CurrentLevel)", "RTID(CH@CurrentLevel)" ] ]
			}
		}, {
			"aliases": [ "Jam8bit" ],
			"objclass": "SpawnZombiesJitteredWaveActionProps",
			"objdata": {
				"NotificationEvents": [ "jam_8bit" ]
			}
		}, {
			"aliases": [ "BossSpawn" ],
			"objclass": "SpawnZombiesJitteredWaveActionProps",
			"objdata": {
				"Zombies": [ {
						"Type": "RTID(boss@CurrentLevel)"
					} ]
			}
		}, {
			"aliases": [ "Wave1" ],
			"objclass": "SpawnZombiesJitteredWaveActionProps",
			"objdata": {
				"Zombies": [ {
						"Row": "2",
						"Type": "RTID(beach_armor1@ZombieTypes)"
					} ]
			}
		}, {
			"aliases": [ "Wave2" ],
			"objclass": "SpawnZombiesJitteredWaveActionProps",
			"objdata": {
				"AdditionalPlantfood": 1,
				"Zombies": [ {
						"Row": "1",
						"Type": "RTID(beach@ZombieTypes)"
					}, {
						"Row": "4",
						"Type": "RTID(lostcity_jane@ZombieTypes)"
					} ]
			}
		}, {
			"aliases": [ "Wave3" ],
			"objclass": "SpawnZombiesJitteredWaveActionProps",
			"objdata": {
				"Zombies": [ {
						"Row": "3",
						"Type": "RTID(beach_armor2@ZombieTypes)"
					} ]
			}
		}, {
			"aliases": [ "Wave4" ],
			"objclass": "SpawnZombiesJitteredWaveActionProps",
			"objdata": {
				"Zombies": [ {
						"Row": "2",
						"Type": "RTID(lostcity_jane@ZombieTypes)"
					}, {
						"Row": "5",
						"Type": "RTID(beach_armor2@ZombieTypes)"
					} ]
			}
		}, {
			"aliases": [ "Wave5" ],
			"objclass": "SpawnZombiesJitteredWaveActionProps",
			"objdata": {
				"Zombies": [ {
						"Row": "1",
						"Type": "RTID(beach_armor1@ZombieTypes)"
					}, {
						"Row": "2",
						"Type": "RTID(beach@ZombieTypes)"
					}, {
						"Row": "3",
						"Type": "RTID(beach_armor1@ZombieTypes)"
					}, {
						"Row": "5",
						"Type": "RTID(beach_armor1@ZombieTypes)"
					} ]
			}
		}, {
			"aliases": [ "Wave6" ],
			"objclass": "SpawnZombiesJitteredWaveActionProps",
			"objdata": {
				"Zombies": [ {
						"Row": "1",
						"Type": "RTID(lostcity_jane@ZombieTypes)"
					}, {
						"Row": "2",
						"Type": "RTID(beach_armor2@ZombieTypes)"
					}, {
						"Row": "4",
						"Type": "RTID(lostcity_jane@ZombieTypes)"
					} ]
			}
		}, {
			"aliases": [ "Wave7" ],
			"objclass": "SpawnZombiesJitteredWaveActionProps",
			"objdata": {
				"Zombies": [ {
						"Row": "1",
						"Type": "RTID(beach@ZombieTypes)"
					}, {
						"Row": "2",
						"Type": "RTID(beach@ZombieTypes)"
					}, {
						"Row": "3",
						"Type": "RTID(beach_armor2@ZombieTypes)"
					}, {
						"Row": "4",
						"Type": "RTID(beach@ZombieTypes)"
					}, {
						"Row": "5",
						"Type": "RTID(beach_armor1@ZombieTypes)"
					}, {
						"Row": "3",
						"Type": "RTID(beach@ZombieTypes)"
					} ]
			}
		}, {
			"aliases": [ "Wave8" ],
			"objclass": "SpawnZombiesJitteredWaveActionProps",
			"objdata": {
				"Zombies": [ {
						"Row": "1",
						"Type": "RTID(football@ZombieTypes)"
					}, {
						"Row": "2",
						"Type": "RTID(beach_armor1@ZombieTypes)"
					}, {
						"Row": "3",
						"Type": "RTID(beach_armor1@ZombieTypes)"
					}, {
						"Row": "4",
						"Type": "RTID(beach_armor1@ZombieTypes)"
					}, {
						"Row": "5",
						"Type": "RTID(beach_armor1@ZombieTypes)"
					}, {
						"Row": "1",
						"Type": "RTID(beach@ZombieTypes)"
					}, {
						"Row": "2",
						"Type": "RTID(beach@ZombieTypes)"
					}, {
						"Row": "3",
						"Type": "RTID(beach@ZombieTypes)"
					}, {
						"Row": "4",
						"Type": "RTID(beach@ZombieTypes)"
					}, {
						"Row": "5",
						"Type": "RTID(beach_armor1@ZombieTypes)"
					} ]
			}
		}, {
			"aliases": [ "Wave9" ],
			"objclass": "SpawnZombiesJitteredWaveActionProps",
			"objdata": {
				"Zombies": [ {
						"Row": "1",
						"Type": "RTID(lostcity_jane@ZombieTypes)"
					}, {
						"Row": "2",
						"Type": "RTID(lostcity_jane@ZombieTypes)"
					}, {
						"Row": "3",
						"Type": "RTID(lostcity_jane@ZombieTypes)"
					}, {
						"Row": "4",
						"Type": "RTID(lostcity_jane@ZombieTypes)"
					}, {
						"Row": "5",
						"Type": "RTID(lostcity_jane@ZombieTypes)"
					}, {
						"Row": "2",
						"Type": "RTID(beach_armor1@ZombieTypes)"
					}, {
						"Row": "4",
						"Type": "RTID(beach_armor1@ZombieTypes)"
					} ]
			}
		}, {
			"aliases": [ "Wave10" ],
			"objclass": "SpawnZombiesJitteredWaveActionProps",
			"objdata": {
				"AdditionalPlantfood": 1,
				"Zombies": [ {
						"Row": "1",
						"Type": "RTID(beach@ZombieTypes)"
					}, {
						"Row": "2",
						"Type": "RTID(beach_armor2@ZombieTypes)"
					}, {
						"Row": "3",
						"Type": "RTID(beach_armor2@ZombieTypes)"
					}, {
						"Row": "4",
						"Type": "RTID(beach_armor1@ZombieTypes)"
					}, {
						"Row": "5",
						"Type": "RTID(beach_armor2@ZombieTypes)"
					}, {
						"Row": "1",
						"Type": "RTID(beach@ZombieTypes)"
					} ]
			}
		}, {
			"aliases": [ "Wave11" ],
			"objclass": "SpawnZombiesJitteredWaveActionProps",
			"objdata": {
				"Zombies": [ {
						"Row": "1",
						"Type": "RTID(beach_armor1@ZombieTypes)"
					}, {
						"Row": "4",
						"Type": "RTID(football@ZombieTypes)"
					} ]
			}
		}, {
			"aliases": [ "Wave12" ],
			"objclass": "SpawnZombiesJitteredWaveActionProps",
			"objdata": {
				"Zombies": [ {
						"Row": "1",
						"Type": "RTID(beach_armor2@ZombieTypes)"
					}, {
						"Row": "2",
						"Type": "RTID(beach_armor2@ZombieTypes)"
					}, {
						"Row": "3",
						"Type": "RTID(beach_armor1@ZombieTypes)"
					}, {
						"Row": "4",
						"Type": "RTID(beach_armor1@ZombieTypes)"
					}, {
						"Row": "5",
						"Type": "RTID(beach_armor2@ZombieTypes)"
					}, {
						"Row": "1",
						"Type": "RTID(lostcity_jane@ZombieTypes)"
					}, {
						"Row": "2",
						"Type": "RTID(lostcity_jane@ZombieTypes)"
					} ]
			}
		}, {
			"aliases": [ "Wave13" ],
			"objclass": "SpawnZombiesJitteredWaveActionProps",
			"objdata": {
				"Zombies": [ {
						"Row": "1",
						"Type": "RTID(lostcity_jane@ZombieTypes)"
					}, {
						"Row": "3",
						"Type": "RTID(football@ZombieTypes)"
					}, {
						"Row": "4",
						"Type": "RTID(beach_armor1@ZombieTypes)"
					}, {
						"Row": "5",
						"Type": "RTID(lostcity_jane@ZombieTypes)"
					} ]
			}
		}, {
			"aliases": [ "Wave14" ],
			"objclass": "SpawnZombiesJitteredWaveActionProps",
			"objdata": {
				"Zombies": [ {
						"Row": "1",
						"Type": "RTID(beach_armor1@ZombieTypes)"
					}, {
						"Row": "2",
						"Type": "RTID(beach_armor1@ZombieTypes)"
					}, {
						"Row": "3",
						"Type": "RTID(beach_armor2@ZombieTypes)"
					}, {
						"Row": "4",
						"Type": "RTID(beach_armor2@ZombieTypes)"
					}, {
						"Row": "5",
						"Type": "RTID(beach_armor1@ZombieTypes)"
					}, {
						"Row": "1",
						"Type": "RTID(lostcity_jane@ZombieTypes)"
					}, {
						"Row": "2",
						"Type": "RTID(lostcity_jane@ZombieTypes)"
					}, {
						"Row": "4",
						"Type": "RTID(lostcity_jane@ZombieTypes)"
					}, {
						"Row": "5",
						"Type": "RTID(beach_armor1@ZombieTypes)"
					}, {
						"Row": "5",
						"Type": "RTID(lostcity_jane@ZombieTypes)"
					} ]
			}
		}, {
			"aliases": [ "Wave15" ],
			"objclass": "SpawnZombiesJitteredWaveActionProps",
			"objdata": {
				"Zombies": [ {
						"Row": "1",
						"Type": "RTID(beach_armor1@ZombieTypes)"
					}, {
						"Row": "2",
						"Type": "RTID(football@ZombieTypes)"
					}, {
						"Row": "3",
						"Type": "RTID(beach@ZombieTypes)"
					}, {
						"Row": "4",
						"Type": "RTID(beach@ZombieTypes)"
					}, {
						"Row": "5",
						"Type": "RTID(beach@ZombieTypes)"
					}, {
						"Row": "2",
						"Type": "RTID(beach_armor2@ZombieTypes)"
					}, {
						"Row": "4",
						"Type": "RTID(beach@ZombieTypes)"
					} ]
			}
		}, {
			"aliases": [ "Wave16" ],
			"objclass": "SpawnZombiesJitteredWaveActionProps",
			"objdata": {
				"Zombies": [ {
						"Row": "1",
						"Type": "RTID(football_mech@ZombieTypes)"
					}, {
						"Row": "2",
						"Type": "RTID(beach_armor2@ZombieTypes)"
					}, {
						"Row": "3",
						"Type": "RTID(beach_armor2@ZombieTypes)"
					}, {
						"Row": "4",
						"Type": "RTID(football_mech@ZombieTypes)"
					}, {
						"Row": "5",
						"Type": "RTID(beach_armor2@ZombieTypes)"
					}, {
						"Row": "1",
						"Type": "RTID(beach_armor1@ZombieTypes)"
					}, {
						"Row": "2",
						"Type": "RTID(lostcity_jane@ZombieTypes)"
					}, {
						"Row": "3",
						"Type": "RTID(lostcity_jane@ZombieTypes)"
					}, {
						"Row": "4",
						"Type": "RTID(beach_armor1@ZombieTypes)"
					}, {
						"Row": "5",
						"Type": "RTID(lostcity_jane@ZombieTypes)"
					}, {
						"Row": "1",
						"Type": "RTID(beach@ZombieTypes)"
					}, {
						"Row": "2",
						"Type": "RTID(beach@ZombieTypes)"
					}, {
						"Row": "4",
						"Type": "RTID(beach@ZombieTypes)"
					}, {
						"Row": "5",
						"Type": "RTID(beach@ZombieTypes)"
					} ]
			}
		}, {
			"aliases": [ "Wave17" ],
			"objclass": "SpawnZombiesJitteredWaveActionProps",
			"objdata": {
				"Zombies": [ {
						"Row": "1",
						"Type": "RTID(football@ZombieTypes)"
					}, {
						"Row": "2",
						"Type": "RTID(beach_armor2@ZombieTypes)"
					}, {
						"Row": "3",
						"Type": "RTID(football@ZombieTypes)"
					}, {
						"Row": "4",
						"Type": "RTID(beach_armor1@ZombieTypes)"
					}, {
						"Row": "5",
						"Type": "RTID(beach_armor2@ZombieTypes)"
					}, {
						"Row": "1",
						"Type": "RTID(beach_armor1@ZombieTypes)"
					}, {
						"Row": "3",
						"Type": "RTID(beach_armor1@ZombieTypes)"
					} ]
			}
		}, {
			"aliases": [ "Wave18" ],
			"objclass": "SpawnZombiesJitteredWaveActionProps",
			"objdata": {
				"Zombies": [ {
						"Row": "1",
						"Type": "RTID(beach_armor1@ZombieTypes)"
					}, {
						"Row": "2",
						"Type": "RTID(beach_armor2@ZombieTypes)"
					}, {
						"Row": "3",
						"Type": "RTID(beach_armor1@ZombieTypes)"
					}, {
						"Row": "4",
						"Type": "RTID(beach_armor1@ZombieTypes)"
					}, {
						"Row": "5",
						"Type": "RTID(football_mech@ZombieTypes)"
					}, {
						"Row": "2",
						"Type": "RTID(beach_armor2@ZombieTypes)"
					}, {
						"Row": "3",
						"Type": "RTID(lostcity_jane@ZombieTypes)"
					}, {
						"Row": "5",
						"Type": "RTID(lostcity_jane@ZombieTypes)"
					}, {
						"Row": "2",
						"Type": "RTID(beach_armor2@ZombieTypes)"
					} ]
			}
		}, {
			"aliases": [ "Wave19" ],
			"objclass": "SpawnZombiesJitteredWaveActionProps",
			"objdata": {
				"Zombies": [ {
						"Row": "1",
						"Type": "RTID(football_mech@ZombieTypes)"
					}, {
						"Row": "2",
						"Type": "RTID(beach@ZombieTypes)"
					}, {
						"Row": "3",
						"Type": "RTID(beach@ZombieTypes)"
					}, {
						"Row": "4",
						"Type": "RTID(football@ZombieTypes)"
					}, {
						"Row": "5",
						"Type": "RTID(beach@ZombieTypes)"
					}, {
						"Row": "1",
						"Type": "RTID(beach@ZombieTypes)"
					}, {
						"Row": "2",
						"Type": "RTID(beach@ZombieTypes)"
					}, {
						"Row": "3",
						"Type": "RTID(beach@ZombieTypes)"
					}, {
						"Row": "4",
						"Type": "RTID(football@ZombieTypes)"
					}, {
						"Row": "5",
						"Type": "RTID(beach@ZombieTypes)"
					} ]
			}
		}, {
			"aliases": [ "Wave20" ],
			"objclass": "SpawnZombiesJitteredWaveActionProps",
			"objdata": {
				"Zombies": [ {
						"Row": "1",
						"Type": "RTID(beach_armor2@ZombieTypes)"
					}, {
						"Row": "2",
						"Type": "RTID(beach_armor2@ZombieTypes)"
					}, {
						"Row": "3",
						"Type": "RTID(football_mech@ZombieTypes)"
					}, {
						"Row": "4",
						"Type": "RTID(beach@ZombieTypes)"
					}, {
						"Row": "5",
						"Type": "RTID(beach_armor2@ZombieTypes)"
					}, {
						"Row": "1",
						"Type": "RTID(beach_armor1@ZombieTypes)"
					}, {
						"Row": "2",
						"Type": "RTID(beach_armor2@ZombieTypes)"
					}, {
						"Row": "3",
						"Type": "RTID(beach_armor1@ZombieTypes)"
					}, {
						"Row": "4",
						"Type": "RTID(beach@ZombieTypes)"
					}, {
						"Row": "5",
						"Type": "RTID(beach_armor2@ZombieTypes)"
					}, {
						"Row": "5",
						"Type": "RTID(beach@ZombieTypes)"
					} ]
			}
		}, {
			"aliases": [ "Wave21" ],
			"objclass": "SpawnZombiesJitteredWaveActionProps",
			"objdata": {
				"Zombies": [ {
						"Row": "1",
						"Type": "RTID(football@ZombieTypes)"
					}, {
						"Row": "2",
						"Type": "RTID(football@ZombieTypes)"
					}, {
						"Row": "3",
						"Type": "RTID(beach_armor2@ZombieTypes)"
					}, {
						"Row": "4",
						"Type": "RTID(beach_armor2@ZombieTypes)"
					}, {
						"Row": "5",
						"Type": "RTID(beach_armor2@ZombieTypes)"
					}, {
						"Row": "1",
						"Type": "RTID(lostcity_jane@ZombieTypes)"
					}, {
						"Row": "2",
						"Type": "RTID(lostcity_jane@ZombieTypes)"
					}, {
						"Row": "3",
						"Type": "RTID(beach_armor1@ZombieTypes)"
					}, {
						"Row": "4",
						"Type": "RTID(beach_armor1@ZombieTypes)"
					}, {
						"Row": "5",
						"Type": "RTID(beach_armor1@ZombieTypes)"
					} ]
			}
		}, {
			"aliases": [ "Wave22" ],
			"objclass": "SpawnZombiesJitteredWaveActionProps",
			"objdata": {
				"Zombies": [ {
						"Row": "1",
						"Type": "RTID(beach_armor2@ZombieTypes)"
					}, {
						"Row": "2",
						"Type": "RTID(beach_armor2@ZombieTypes)"
					}, {
						"Row": "3",
						"Type": "RTID(football@ZombieTypes)"
					}, {
						"Row": "4",
						"Type": "RTID(football_mech@ZombieTypes)"
					}, {
						"Row": "5",
						"Type": "RTID(football_mech@ZombieTypes)"
					}, {
						"Row": "1",
						"Type": "RTID(lostcity_jane@ZombieTypes)"
					}, {
						"Row": "2",
						"Type": "RTID(beach_armor1@ZombieTypes)"
					}, {
						"Row": "3",
						"Type": "RTID(beach@ZombieTypes)"
					}, {
						"Row": "4",
						"Type": "RTID(beach@ZombieTypes)"
					}, {
						"Row": "5",
						"Type": "RTID(beach@ZombieTypes)"
					}, {
						"Row": "3",
						"Type": "RTID(beach@ZombieTypes)"
					}, {
						"Row": "4",
						"Type": "RTID(beach@ZombieTypes)"
					}, {
						"Row": "5",
						"Type": "RTID(beach@ZombieTypes)"
					} ]
			}
		}, {
			"aliases": [ "Wave23" ],
			"objclass": "SpawnZombiesJitteredWaveActionProps",
			"objdata": {
				"Zombies": [ {
						"Row": "1",
						"Type": "RTID(beach_armor2@ZombieTypes)"
					}, {
						"Row": "2",
						"Type": "RTID(beach_armor2@ZombieTypes)"
					}, {
						"Row": "3",
						"Type": "RTID(beach_armor2@ZombieTypes)"
					}, {
						"Row": "4",
						"Type": "RTID(beach_armor2@ZombieTypes)"
					}, {
						"Row": "5",
						"Type": "RTID(beach_armor2@ZombieTypes)"
					}, {
						"Row": "1",
						"Type": "RTID(beach_armor2@ZombieTypes)"
					}, {
						"Row": "2",
						"Type": "RTID(beach_armor2@ZombieTypes)"
					}, {
						"Row": "3",
						"Type": "RTID(beach_armor2@ZombieTypes)"
					}, {
						"Row": "4",
						"Type": "RTID(beach_armor2@ZombieTypes)"
					}, {
						"Row": "5",
						"Type": "RTID(beach_armor2@ZombieTypes)"
					}, {
						"Row": "1",
						"Type": "RTID(lostcity_jane@ZombieTypes)"
					}, {
						"Row": "2",
						"Type": "RTID(beach_armor2@ZombieTypes)"
					}, {
						"Row": "3",
						"Type": "RTID(lostcity_jane@ZombieTypes)"
					}, {
						"Row": "4",
						"Type": "RTID(lostcity_jane@ZombieTypes)"
					}, {
						"Row": "5",
						"Type": "RTID(beach_armor2@ZombieTypes)"
					} ]
			}
		}, {
			"aliases": [ "Wave24" ],
			"objclass": "SpawnZombiesJitteredWaveActionProps",
			"objdata": {
				"Zombies": [ {
						"Row": "1",
						"Type": "RTID(football_mech@ZombieTypes)"
					}, {
						"Row": "2",
						"Type": "RTID(football_mech@ZombieTypes)"
					}, {
						"Row": "3",
						"Type": "RTID(beach_armor2@ZombieTypes)"
					}, {
						"Row": "4",
						"Type": "RTID(football_mech@ZombieTypes)"
					}, {
						"Row": "5",
						"Type": "RTID(beach_armor2@ZombieTypes)"
					}, {
						"Row": "1",
						"Type": "RTID(football@ZombieTypes)"
					}, {
						"Row": "2",
						"Type": "RTID(football@ZombieTypes)"
					}, {
						"Row": "3",
						"Type": "RTID(beach_armor2@ZombieTypes)"
					}, {
						"Row": "4",
						"Type": "RTID(football@ZombieTypes)"
					}, {
						"Row": "5",
						"Type": "RTID(beach_armor2@ZombieTypes)"
					}, {
						"Row": "1",
						"Type": "RTID(beach_armor1@ZombieTypes)"
					}, {
						"Row": "2",
						"Type": "RTID(beach_armor1@ZombieTypes)"
					}, {
						"Row": "3",
						"Type": "RTID(beach_armor2@ZombieTypes)"
					}, {
						"Row": "4",
						"Type": "RTID(beach_armor1@ZombieTypes)"
					}, {
						"Row": "5",
						"Type": "RTID(beach_armor2@ZombieTypes)"
					}, {
						"Row": "1",
						"Type": "RTID(lostcity_jane@ZombieTypes)"
					}, {
						"Row": "2",
						"Type": "RTID(lostcity_jane@ZombieTypes)"
					}, {
						"Row": "3",
						"Type": "RTID(lostcity_jane@ZombieTypes)"
					}, {
						"Row": "4",
						"Type": "RTID(lostcity_jane@ZombieTypes)"
					}, {
						"Row": "5",
						"Type": "RTID(lostcity_jane@ZombieTypes)"
					} ]
			}
		}, {
			"aliases": [ "CHMessage" ],
			"objclass": "BeachStageEventZombieSpawnerProps",
			"objdata": {
				"ColumnEnd": 0,
				"ColumnStart": 0,
				"GroupSize": 0,
				"TimeBeforeFullSpawn": "0.5",
				"TimeBetweenGroups": "0.25",
				"WaveStartMessage": "Charming Hits!",
				"ZombieCount": 0,
				"ZombieName": "ra"
			}
		}, {
			"aliases": [ "CH" ],
			"objclass": "SpawnZombiesFromGroundSpawnerProps",
			"objdata": {
				"ColumnStart": 5,
				"ColumnEnd": 6,
				"Zombies": [ {
						"Type": "RTID(eighties_boombox@ZombieTypes)"
					}, {
						"Type": "RTID(eighties_boombox@ZombieTypes)"
					} ]
			}
		}, {
			"objclass": "ZombieType",
			"aliases": [ "boss" ],
			"objdata": {
				"TypeName": "iceage_hunter",
				"ZombieClass": "ZombieIceAgeHunter",
				"Properties": "RTID(ZombieBoss@CurrentLevel)",
				"ResourceGroups": [ "ZombieIceAgeHunterGroup", "PlantBowlingBulb" ],
				"AudioGroups": [ "PlantPeashooterAudio" ],
				"AnimRigClass": "ZombieAnimRig_Hunter",
				"PopAnim": "POPANIM_ZOMBIE_ZOMBIE_ICEAGE_HUNTER",
				"HomeWorld": "iceage",
				"Placeable": true
			}
		}, {
			"objclass": "ZombieIceAgeHunterProps",
			"aliases": [ "ZombieBoss" ],
			"objdata": {
				"Speed": 0.08,
				"Hitpoints": 5400,
				"EatDPS": 400,
				"CanSpawnPlantFood": false,
				"ChillInsteadOfFreeze": true,
				"Actions": [ "RTID(ZombieBossAction@CurrentLevel)" ],
				"HitRect": {
					"mHeight": 95,
					"mWidth": 30,
					"mX": 7,
					"mY": 10
				},
				"AttackRect": {
					"mHeight": 0,
					"mWidth": 0,
					"mX": 80000,
					"mY": 80000
				},
				"NearAttackRange": 0,
				"FarAttackRange": 9,
				"SnowballsPerBarrage": 4,
				"ArtCenter": {
					"x": 90,
					"y": 125
				},
				"ShadowOffset": {
					"x": 10,
					"y": 0,
					"z": 1.2
				},
				"GroundTrackName": "ground_swatch"
			}
		}, {
			"objclass": "ZombieProjectileActionDefinition",
			"aliases": [ "ZombieBossAction" ],
			"objdata": {
				"TimeBeforeFirst": {
					"Min": 10.0,
					"Max": 20.0
				},
				"TimeBetween": {
					"Min": 5.0,
					"Max": 6.0
				},
				"TimeBetweenBarrages": {
					"Min": 25.0,
					"Max": 35.0
				},
				"Projectile": "RTID(ZombieBossProjectile@CurrentLevel)",
				"ProjectileSound": "",
				"SpawnOffset": {
					"x": -50.0,
					"y": 0.0,
					"z": 30.0
				},
				"ApexHeight": 100,
				"TimeUntilHit": 0.75
			}
		}, {
			"objclass": "BowlingBulbProjectileProps",
			"aliases": [ "ZombieBossProjectile" ],
			"objdata": {
				"ClassName": "BowlingBulbProjectile",
				"BaseDamage": 30,
				"SplashDamage": 0,
				"BounceAngleInDegrees": 45.0,
				"BounceOutwardTendency": 0.5,
				"HitsUntilFirstAward": 1,
				"HitsUntilRepeatAward": 1,
				"LootAwardOnHits": "",
				"CollisionFlags": [ "griditems", "plants", "all_zombies" ],
				"DamageFlags": [ "lobbed", "shooter" ],
				"InitialVelocity": [ {
						"Min": -300.0,
						"Max": -300.0
					}, {
						"Min": 0.0,
						"Max": 0.0
					}, {
						"Min": 0.0,
						"Max": 0.0
					} ],
				"InitialAcceleration": [ {
						"Min": 0.0,
						"Max": 0.0
					}, {
						"Min": 0.0,
						"Max": 0.0
					}, {
						"Min": 0.0,
						"Max": 0.0
					} ],
				"RenderColor": {
					"mRed": 75,
					"mGreen": 50,
					"mBlue": 100,
					"mAlpha": 220
				},
				"InitialScale": {
					"Min": 1.0,
					"Max": 1.0
				},
				"HasShadow": true,
				"DiesOnImpact": false,
				"AttachedPAM": "POPANIM_EFFECTS_BOWLINGBULB_PROJECTILE1",
				"AttachedPAMOffset": {
					"x": -100,
					"y": -97
				},
				"AttachedPAMAnimationToPlay": [ "animation" ],
				"ImpactSoundEvent": "Play_Plant_BowlingBulb_Impact",
				"CollisionRect": {
					"mX": -5.0,
					"mY": 0.0,
					"mWidth": 10.0,
					"mHeight": 10.0
				}
			}
		}, {
			"aliases": [ "TrapTileProps_1" ],
			"objclass": "GridItemProjectileTrapProps",
			"objdata": {
				"Height": "ground",
				"PopAnim": "POPANIM_BACKGROUNDS_BOULDERTILE",
				"PopAnimRenderOffset": {
					"x": 8000,
					"y": 8000
				},
				"PopAnimRigClass": "EffectAnimRig_SwitchTile",
				"ProjectileFireOriginOffset": {
					"x": -1664.0,
					"y": 0.0,
					"z": 30.0
				},
				"ProjectileTypeToSpawn": "RTID(KillConsultant@CurrentLevel)",
				"TileBaseAnimation": "bouldertile",
				"TimeBetweenTriggersInSeconds": 0.1,
				"TriggerRect": {
					"mHeight": 60.0,
					"mWidth": 120.0,
					"mX": -60.0,
					"mY": -60.0
				},
				"TriggeringEntityTypes": [ "zombie" ]
			}
		}, {
			"objclass": "ProjectilePropertySheet",
			"aliases": [ "KillConsultant" ],
			"objdata": {
				"BaseDamage": 0.1,
				"SplashDamage": 0.1,
				"SplashRadius": 80000,
				"DiesOnImpact": true,
				"CollisionFlags": [ "ground" ],
				"DamageFlags": [ "no_flash" ],
				"InitialVelocity": [ {
						"Min": 0.0,
						"Max": 0.0
					}, {
						"Min": 0.0,
						"Max": 0.0
					}, {
						"Min": -100.0,
						"Max": -100.0
					} ],
				"InitialScale": {
					"Min": 0,
					"Max": 0
				},
				"AttachedPAM": "",
				"AttachedPAMAnimationToPlay": [],
				"ImpactSoundEvent": "",
				"ImpactPAM": "",
				"ImpactPAMAnimationToPlay": [ "" ],
				"ImpactOffset": [ {
						"Min": 0.0,
						"Max": 0.0
					}, {
						"Min": -16.0,
						"Max": 16.0
					} ],
				"CollisionRect": {
					"mX": -20.0,
					"mY": -20.0,
					"mWidth": 40.0,
					"mHeight": 40.0
				}
			}
		}, {
			"aliases": [ "ZombieConsultantLaneChange" ],
			"objclass": "ZombieZCorpConsultantProps",
			"objdata": {
				"ArtCenter": {
					"x": 120,
					"y": 170
				},
				"ArtCenterBurnEffectOffset": {
					"x": -45,
					"y": -45
				},
				"AttackRect": {
					"mHeight": 95,
					"mWidth": 576,
					"mX": -1536,
					"mY": 0
				},
				"CanSpawnPlantFood": true,
				"Cost": 150,
				"EatDPS": 0,
				"ForwardShovePercentage": 0.0,
				"ShoveHeight": 0.5,
				"ShoveTime": 0.5,
				"SlideTime": 0.3,
				"SlideCooldown": 0.1,
				"TimeBetweenDirectionChanges": 9999,
				"ShoveExcludeList": {
					"ListType": "includelist",
					"List": [ "ZombieIceAgeHunter" ]
				},
				"GroundTrackName": "ground_swatch",
				"HitRect": {
					"mHeight": 95,
					"mWidth": 32,
					"mX": 10,
					"mY": 10
				},
				"Hitpoints": 0.1,
				"ShadowOffset": {
					"x": 0,
					"y": 0,
					"z": 1.2
				},
				"Speed": 0.0,
				"WavePointCost": 700,
				"Weight": 4000
			}
		} ],
	"version": 1
}